fiona/_path.py
fiona/enums.py
fiona/_err.cpython-38-darwin.so
fiona/crs.pxd
fiona/env.py
fiona/compat.py
fiona/_transform.cpython-38-darwin.so
fiona/_csl.pxd
fiona/ogrext1.pxd
fiona/schema.cpython-38-darwin.so
fiona/_geometry.pxd
fiona/ogrext2.pxd
fiona/io.py
fiona/ogrext3.pxd
fiona/drvsupport.py
fiona/session.py
fiona/inspector.py
fiona/__init__.py
fiona/_env.pxd
fiona/features.py
fiona/_vsiopener.cpython-38-darwin.so
fiona/logutils.py
fiona/ogrext.cpython-38-darwin.so
fiona/model.py
fiona/crs.cpython-38-darwin.so
fiona/rfc3339.py
fiona/vfs.py
fiona/_env.cpython-38-darwin.so
fiona/transform.py
fiona/collection.py
fiona/_show_versions.py
fiona/_cpl.pxd
fiona/errors.py
fiona/_geometry.cpython-38-darwin.so
fiona/_vsiopener.pxd
fiona/gdal.pxi
fiona/path.py
fiona/_err.pxd
fiona/abc.py
fiona/meta.py
fiona/proj_data/proj.db
fiona/proj_data/nad83
fiona/proj_data/CH
fiona/proj_data/world
fiona/proj_data/proj.ini
fiona/proj_data/nad.lst
fiona/proj_data/ITRF2000
fiona/proj_data/ITRF2008
fiona/proj_data/triangulation.schema.json
fiona/proj_data/deformation_model.schema.json
fiona/proj_data/nad27
fiona/proj_data/projjson.schema.json
fiona/proj_data/GL27
fiona/proj_data/ITRF2014
fiona/proj_data/other.extra
fiona/_vendor/snuggs.py
fiona/_vendor/munch/__init__.py
fiona/fio/options.py
fiona/fio/collect.py
fiona/fio/distrib.py
fiona/fio/env.py
fiona/fio/insp.py
fiona/fio/cat.py
fiona/fio/__init__.py
fiona/fio/features.py
fiona/fio/ls.py
fiona/fio/rm.py
fiona/fio/dump.py
fiona/fio/calc.py
fiona/fio/load.py
fiona/fio/main.py
fiona/fio/info.py
fiona/fio/helpers.py
fiona/fio/bounds.py
fiona/.dylibs/libsqlite3.0.dylib
fiona/.dylibs/libpcre2-8.0.dylib
fiona/.dylibs/libproj.25.9.4.1.dylib
fiona/.dylibs/libpng16.16.dylib
fiona/.dylibs/libssl.1.1.dylib
fiona/.dylibs/libjpeg.9.dylib
fiona/.dylibs/libnghttp2.14.dylib
fiona/.dylibs/libcurl.4.dylib
fiona/.dylibs/libgdal.35.3.9.2.dylib
fiona-1.10.0.dist-info/RECORD
fiona-1.10.0.dist-info/WHEEL
fiona-1.10.0.dist-info/entry_points.txt
fiona-1.10.0.dist-info/top_level.txt
fiona-1.10.0.dist-info/LICENSE.txt
fiona-1.10.0.dist-info/METADATA
